alphasense_api_sdk/__init__.py
alphasense_api_sdk/async_base_client.py
alphasense_api_sdk/auth.py
alphasense_api_sdk/base_model.py
alphasense_api_sdk/base_operation.py
alphasense_api_sdk/client.py
alphasense_api_sdk/config.py
alphasense_api_sdk/custom_fields.py
alphasense_api_sdk/custom_mutations.py
alphasense_api_sdk/custom_queries.py
alphasense_api_sdk/custom_typing_fields.py
alphasense_api_sdk/enums.py
alphasense_api_sdk/exceptions.py
alphasense_api_sdk/input_types.py
alphasense_api_sdk-0.1.10.dist-info/METADATA
alphasense_api_sdk-0.1.10.dist-info/WHEEL
alphasense_api_sdk-0.1.10.dist-info/licenses/LICENSE
alphasense_api_sdk-0.1.10.dist-info/RECORD
